{
  "tasks": [
    {
      "id": 1,
      "text": "t1",
      "day": "d.toString()",
      "reminder": true
    },
    {
      "id": 2,
      "text": "t2",
      "day": "d.toString()",
      "reminder": true
    },
    {
      "id": 7,
      "text": "brilliant",
      "day": "",
      "reminder": false
    },
    {
      "text": "dfbdfb",
      "day": "",
      "reminder": false,
      "id": 9
    },
    {
      "text": "ANOTHER TASK",
      "day": "TELEGRAM",
      "reminder": false,
      "id": 10
    }
  ]
}